yEscher/__init__.py
yEscher/analysis.py
yEscher/enumETFL.py
yEscher/data/.deprecated/databases/DBnewGeneAnnotation.tsv
yEscher/data/.deprecated/databases/FAEgeneNames.tsv
yEscher/data/.deprecated/databases/TransRxnGeneAnnotation.tsv
yEscher/data/.deprecated/databases/Yeast7.6MNXMetMappingList.tsv
yEscher/data/.deprecated/databases/Yeast7.6MNXRxnMappingList.tsv
yEscher/data/.deprecated/modelCuration/Biolog_newRxnMatrix.tsv
yEscher/data/.deprecated/modelCuration/Biolog_newRxnMetAnnotation.tsv
yEscher/data/.deprecated/modelCuration/Biolog_newRxnProp.tsv
yEscher/data/.deprecated/modelCuration/Biomass_newRxnMatrix.tsv
yEscher/data/.deprecated/modelCuration/Biomass_newRxnMet.tsv
yEscher/data/.deprecated/modelCuration/Biomass_newRxnProp.tsv
yEscher/data/.deprecated/modelCuration/FAEnewRxnMatrix.tsv
yEscher/data/.deprecated/modelCuration/FAEnewRxnMetAnnotation.tsv
yEscher/data/.deprecated/modelCuration/FAEnewRxnProp.tsv
yEscher/data/.deprecated/modelCuration/GapfillingnewRxnMatrix.tsv
yEscher/data/.deprecated/modelCuration/GapfillingnewRxnProp.tsv
yEscher/data/.deprecated/modelCuration/MetaCyc_deltaG.tsv
yEscher/data/.deprecated/modelCuration/Metabolomics_newRxnMatrix.tsv
yEscher/data/.deprecated/modelCuration/Metabolomics_newRxnMetAnnotation.tsv
yEscher/data/.deprecated/modelCuration/Metabolomics_newRxnProp.tsv
yEscher/data/.deprecated/modelCuration/Missingmetaboliteformulas.tsv
yEscher/data/.deprecated/modelCuration/grpContribution_deltaG.tsv
yEscher/data/.deprecated/modelCuration/iSce926curatedGeneRules.tsv
yEscher/data/.deprecated/modelCuration/iSce926newGenes.tsv
yEscher/data/.deprecated/modelCuration/memote_revIdx.tsv
yEscher/data/.deprecated/modelCuration/metabolite_manual_curation.tsv
yEscher/data/.deprecated/modelCuration/modMetsandSmatrix.tsv
yEscher/data/.deprecated/modelCuration/modifyID.tsv
yEscher/data/.deprecated/modelCuration/rxnDirectionInfo.tsv
yEscher/data/.deprecated/modelCuration/volatileSulfurCompounds/VoSulGenes.tsv
yescher-1.0.1.dist-info/LICENSE
yescher-1.0.1.dist-info/METADATA
yescher-1.0.1.dist-info/WHEEL
yescher-1.0.1.dist-info/top_level.txt
yescher-1.0.1.dist-info/RECORD
