Metadata-Version: 2.1
Name: yescher
Version: 1.0.1
Summary: Simulate metabolic flux distributions, gene knockouts, and dynamic modeling for S. cerevisiae
Home-page: https://github.com/Shyamsaibethina/yEscher
Author: Shyam Sai Bethina
Author-email: shyamsaibethina@gmail.com
License: MIT
Keywords: yeast,escher,pytfa,ME models,thermodynamics,flux analysis,expression
Platform: UNKNOWN
Classifier: Development Status :: 4 - Beta
Classifier: Intended Audience :: Science/Research
Classifier: Topic :: Scientific/Engineering :: Bio-Informatics
Classifier: Environment :: Console
Classifier: License :: OSI Approved :: MIT License
Classifier: Programming Language :: Python :: 3.9
Requires-Python: >=2.7, !=3.0.*, !=3.1.*, !=3.2.*, !=3.3.*, <4
License-File: LICENSE
Requires-Dist: beautifulsoup4
Requires-Dist: Bio
Requires-Dist: bokeh (<2.5.0,>=2.4.0)
Requires-Dist: cobra (<=0.24)
Requires-Dist: gurobipy
Requires-Dist: joblib
Requires-Dist: numpy
Requires-Dist: optlang
Requires-Dist: pandas
Requires-Dist: pymysql
Requires-Dist: pytest
Requires-Dist: pytfa
Requires-Dist: python-dotenv
Requires-Dist: PyYAML
Requires-Dist: rdkit
Requires-Dist: Requests
Requires-Dist: scikit-learn
Requires-Dist: scipy
Requires-Dist: setuptools
Requires-Dist: sphinx-rtd-theme
Requires-Dist: SQLAlchemy
Requires-Dist: sympy
Requires-Dist: tqdm
Requires-Dist: pyqt5 (<5.13)
Requires-Dist: pyqtwebengine (<5.13)
Requires-Dist: pathlib
Requires-Dist: nbconvert (<8.0.0,>=7.11.0)
Requires-Dist: pluggy (>=1.0.0)
Requires-Dist: xlrd (<2.0)
